aind_dynamic_foraging_basic_analysis/__init__.py
aind_dynamic_foraging_basic_analysis/data_model/foraging_session.py
aind_dynamic_foraging_basic_analysis/licks/annotation.py
aind_dynamic_foraging_basic_analysis/licks/lick_analysis.py
aind_dynamic_foraging_basic_analysis/licks/plot_interlick_interval.py
aind_dynamic_foraging_basic_analysis/metrics/event_rate.py
aind_dynamic_foraging_basic_analysis/metrics/foraging_efficiency.py
aind_dynamic_foraging_basic_analysis/metrics/snr_kurtosis.py
aind_dynamic_foraging_basic_analysis/metrics/trial_metrics.py
aind_dynamic_foraging_basic_analysis/plot/plot_fip.py
aind_dynamic_foraging_basic_analysis/plot/plot_foraging_session.py
aind_dynamic_foraging_basic_analysis/plot/plot_foraging_session_plotly.py
aind_dynamic_foraging_basic_analysis/plot/plot_session_scroller.py
aind_dynamic_foraging_basic_analysis/plot/style.py
aind_dynamic_foraging_basic_analysis-0.3.37.dist-info/licenses/LICENSE
aind_dynamic_foraging_basic_analysis-0.3.37.dist-info/METADATA
aind_dynamic_foraging_basic_analysis-0.3.37.dist-info/WHEEL
aind_dynamic_foraging_basic_analysis-0.3.37.dist-info/top_level.txt
aind_dynamic_foraging_basic_analysis-0.3.37.dist-info/RECORD
