Metadata-Version: 2.4
Name: aind-dynamic-foraging-basic-analysis
Version: 0.3.37
Summary: Generated from aind-library-template
Author: Allen Institute for Neural Dynamics
License: MIT
Classifier: Programming Language :: Python :: 3
Requires-Python: >=3.9
License-File: LICENSE
Requires-Dist: numpy
Requires-Dist: scipy
Requires-Dist: matplotlib
Requires-Dist: plotly
Requires-Dist: pandas
Requires-Dist: pynwb
Requires-Dist: aind_ephys_utils
Requires-Dist: pathlib
Requires-Dist: numpy
Requires-Dist: pydantic
Requires-Dist: hdmf_zarr
Requires-Dist: aind-dynamic-foraging-data-utils>=0.1.25
Requires-Dist: aind_hierarchical_bootstrap
Requires-Dist: aind_dynamic_foraging_models
Provides-Extra: dev
Requires-Dist: black; extra == "dev"
Requires-Dist: coverage; extra == "dev"
Requires-Dist: flake8; extra == "dev"
Requires-Dist: interrogate; extra == "dev"
Requires-Dist: isort; extra == "dev"
Requires-Dist: Sphinx; extra == "dev"
Requires-Dist: furo; extra == "dev"
Requires-Dist: pynwb; extra == "dev"
Dynamic: license-file
